{
  "1": [
    {
      "name": "左慈",
      "skills": [
        "云行雨施",
        "折冲御侮",
        "运筹帷幄"
      ]
    },
    {
      "name": "庞德",
      "skills": [
        "陷阵蹈难",
        "战八方",
        "威名显赫"
      ]
    },
    {
      "name": "关羽",
      "skills": [
        "威震华夏",
        "冲锐巧变",
        "水淹七军"
      ]
    }
  ],
  "2": [
    {
      "name": "曹仁",
      "skills": [
        "固镇襄樊",
        "战八方",
        "十面埋伏"
      ]
    },
    {
      "name": "夏侯渊",
      "skills": [
        "神速奔袭",
        "势如破竹",
        "破军袭敌"
      ]
    },
    {
      "name": "郭嘉",
      "skills": [
        "算无遗策",
        "运筹帷幄",
        "指点乾坤"
      ]
    }
  ],
  "winner": "2",
  "fuzzy_match_failures": [],
  "unmapped_heroes": []
}