{
  "1": [
    {
      "name": "贾诩",
      "skills": [
        "诡道玄机",
        "上智为间",
        "披坚执锐"
      ]
    },
    {
      "name": "曹操",
      "skills": [
        "乱世奸雄",
        "步步为营",
        "百战不殆"
      ]
    },
    {
      "name": "夏侯渊",
      "skills": [
        "神速奔袭",
        "威名显赫",
        "铁骑横冲"
      ]
    }
  ],
  "2": [
    {
      "name": "马超",
      "skills": [
        "纵马横枪",
        "摧坚克难",
        "穷追不舍"
      ]
    },
    {
      "name": "法正",
      "skills": [
        "睹事知机",
        "战八方",
        "决水破敌"
      ]
    },
    {
      "name": "诸葛亮2",
      "skills": [
        "星罗棋布",
        "避其锐气",
        "践墨随敌"
      ]
    }
  ],
  "winner": "2",
  "fuzzy_match_failures": [],
  "unmapped_heroes": []
}