{
  "1": [
    {
      "name": "夏侯惇",
      "skills": [
        "刚烈",
        "挫锐折锋",
        "避其锐气"
      ]
    },
    {
      "name": "贾诩",
      "skills": [
        "诡道玄机",
        "蓄势待发",
        "折冲御侮"
      ]
    },
    {
      "name": "司马懿",
      "skills": [
        "鹰视狼顾",
        "明其虚实",
        "潜龙在渊"
      ]
    }
  ],
  "2": [
    {
      "name": "袁绍",
      "skills": [
        "合聚群雄",
        "铸甲销戈",
        "运筹帷幄"
      ]
    },
    {
      "name": "黄月英",
      "skills": [
        "木牛流马",
        "空城计",
        "指点乾坤"
      ]
    },
    {
      "name": "姜维",
      "skills": [
        "九伐中原",
        "胜敌益强",
        "机变无穷"
      ]
    }
  ],
  "winner": "1",
  "fuzzy_match_failures": [],
  "unmapped_heroes": []
}