{
  "1": [
    {
      "name": "司马懿",
      "skills": [
        "鹰视狼顾",
        "明其虚实",
        "惩前毖后"
      ]
    },
    {
      "name": "曹丕",
      "skills": [
        "权御九锡",
        "坚如磐石",
        "横征暴敛"
      ]
    },
    {
      "name": "荀彧",
      "skills": [
        "建计举人",
        "折冲御侮",
        "青囊急救"
      ]
    }
  ],
  "2": [
    {
      "name": "徐庶",
      "skills": [
        "折节学问",
        "横征暴敛",
        "固若金汤"
      ]
    },
    {
      "name": "司马懿",
      "skills": [
        "鹰视狼顾",
        "神略制变",
        "潜龙在渊"
      ]
    },
    {
      "name": "荀彧",
      "skills": [
        "建计举人",
        "蓄势待发",
        "奇正相生"
      ]
    }
  ],
  "winner": "1",
  "fuzzy_match_failures": [],
  "unmapped_heroes": []
}