{
  "1": [
    {
      "name": "姜维",
      "skills": [
        "九伐中原",
        "胜敌益强",
        "潜龙在渊"
      ]
    },
    {
      "name": "诸葛亮2",
      "skills": [
        "星罗棋布",
        "同舟共济",
        "避其锐气"
      ]
    },
    {
      "name": "庞统",
      "skills": [
        "连环计",
        "挫锐折锋",
        "金城汤池"
      ]
    }
  ],
  "2": [
    {
      "name": "乐进",
      "skills": [
        "每战先登",
        "疾行侧击",
        "无难之志"
      ]
    },
    {
      "name": "马腾",
      "skills": [
        "雄踞西凉",
        "舍生取义",
        "挫锐折锋"
      ]
    },
    {
      "name": "夏侯渊",
      "skills": [
        "神速奔袭",
        "铁骑横冲",
        "兵贵神速"
      ]
    }
  ],
  "winner": "1",
  "fuzzy_match_failures": []
}