{
  "1": [
    {
      "name": "袁术",
      "skills": [
        "僭号天子",
        "百战不殆",
        "折冲御侮"
      ]
    },
    {
      "name": "朱儁",
      "skills": [
        "围师必阙",
        "王佐之才",
        "料事如神"
      ]
    },
    {
      "name": "司马懿",
      "skills": [
        "鹰视狼顾",
        "潜龙在渊",
        "明其虚实"
      ]
    }
  ],
  "2": [
    {
      "name": "陆抗",
      "skills": [
        "决堰倾涛",
        "潜师袭远",
        "诱敌深入"
      ]
    },
    {
      "name": "祝融",
      "skills": [
        "南疆烈刃",
        "洗筋伐髓",
        "十面埋伏"
      ]
    },
    {
      "name": "孙坚2",
      "skills": [
        "诛凶殄逆",
        "锐不可当",
        "势如破竹"
      ]
    }
  ],
  "winner": "1",
  "fuzzy_match_failures": [],
  "season": 15
}
