{
  "1": [
    {
      "name": "大乔",
      "skills": [
        "国色",
        "横征暴敛",
        "践墨随敌"
      ]
    },
    {
      "name": "田丰",
      "skills": [
        "荐计阻敌",
        "运筹帷幄",
        "料事如神"
      ]
    },
    {
      "name": "孙坚2",
      "skills": [
        "诛凶殄逆",
        "文武双全",
        "如有神助"
      ]
    }
  ],
  "2": [
    {
      "name": "陆逊",
      "skills": [
        "火烧连营",
        "明其虚实",
        "韬光养晦"
      ]
    },
    {
      "name": "陆抗",
      "skills": [
        "决堰倾涛",
        "烈火张天",
        "横征暴敛"
      ]
    },
    {
      "name": "左慈",
      "skills": [
        "云行雨施",
        "鸩饮毒弑",
        "折冲御侮"
      ]
    }
  ],
  "winner": "2",
  "fuzzy_match_failures": []
}