{
  "1": [
    {
      "name": "司马懿",
      "skills": [
        "鹰视狼顾",
        "潜龙在渊",
        "未雨绸缪"
      ]
    },
    {
      "name": "邓艾",
      "skills": [
        "屯田令",
        "折冲御侮",
        "决水破敌"
      ]
    },
    {
      "name": "曹丕",
      "skills": [
        "权御九锡",
        "调和阴阳",
        "步步为营"
      ]
    }
  ],
  "2": [
    {
      "name": "貂蝉",
      "skills": [
        "闭月",
        "披坚执锐",
        "避其锐气"
      ]
    },
    {
      "name": "木鹿大王",
      "skills": [
        "驱兽御象",
        "无难之志",
        "战八方"
      ]
    },
    {
      "name": "祝融",
      "skills": [
        "南疆烈刃",
        "锐不可当",
        "威名显赫"
      ]
    }
  ],
  "winner": "1",
  "fuzzy_match_failures": []
}