{
  "1": [
    {
      "name": "周泰",
      "skills": [
        "不屈意志",
        "十面埋伏",
        "断戈夺锋"
      ]
    },
    {
      "name": "诸葛亮2",
      "skills": [
        "星罗棋布",
        "折冲御侮",
        "惩前毖后"
      ]
    },
    {
      "name": "周瑜",
      "skills": [
        "临机制胜",
        "烈火焚营",
        "鸩饮毒弑"
      ]
    }
  ],
  "2": [
    {
      "name": "马超",
      "skills": [
        "纵马横枪",
        "摧坚克难",
        "威名显赫"
      ]
    },
    {
      "name": "曹纯",
      "skills": [
        "天下骁锐",
        "十面埋伏",
        "战八方"
      ]
    },
    {
      "name": "大乔",
      "skills": [
        "国色",
        "避其锐气",
        "断敌粮道"
      ]
    }
  ],
  "winner": "1",
  "fuzzy_match_failures": []
}