{
  "1": [
    {
      "name": "周瑜",
      "skills": [
        "临机制胜",
        "明其虚实",
        "狂风大作"
      ]
    },
    {
      "name": "孙权",
      "skills": [
        "虎踞江东",
        "苦肉计",
        "御敌临前"
      ]
    },
    {
      "name": "步练师",
      "skills": [
        "淑懿之德",
        "运筹帷幄",
        "知人善任"
      ]
    }
  ],
  "2": [
    {
      "name": "徐盛",
      "skills": [
        "百里疑城",
        "避其锐气",
        "忘私相助"
      ]
    },
    {
      "name": "姜维",
      "skills": [
        "九伐中原",
        "惩前毖后",
        "胜敌益强"
      ]
    },
    {
      "name": "法正",
      "skills": [
        "睹事知机",
        "清风驱疾",
        "苦肉计"
      ]
    }
  ],
  "winner": "2",
  "fuzzy_match_failures": []
}