{
  "1": [
    {
      "name": "袁术",
      "skills": [
        "僭号天子",
        "铸甲销戈",
        "任人唯贤"
      ]
    },
    {
      "name": "皇甫嵩2",
      "skills": [
        "兵动若神",
        "固若金汤",
        "洗筋伐髓"
      ]
    },
    {
      "name": "贾诩",
      "skills": [
        "诡道玄机",
        "断敌粮道",
        "横征暴敛"
      ]
    }
  ],
  "2": [
    {
      "name": "魏延",
      "skills": [
        "子午奇谋",
        "定军扬威",
        "断戈夺锋"
      ]
    },
    {
      "name": "周泰",
      "skills": [
        "不屈意志",
        "蹈锋饮血",
        "挫锐折锋"
      ]
    },
    {
      "name": "诸葛瑾",
      "skills": [
        "慎思笃行",
        "料事如神",
        "战八方"
      ]
    }
  ],
  "winner": "1",
  "fuzzy_match_failures": []
}