{
  "1": [
    {
      "name": "曹丕",
      "skills": [
        "权御九锡",
        "以静制动",
        "横征暴敛"
      ]
    },
    {
      "name": "陆逊",
      "skills": [
        "火烧连营",
        "未雨绸缪",
        "如有神助"
      ]
    },
    {
      "name": "大乔",
      "skills": [
        "国色",
        "风助火势",
        "运筹帷幄"
      ]
    }
  ],
  "2": [
    {
      "name": "张飞",
      "skills": [
        "万人之敌",
        "横征暴敛",
        "蹈锋饮血"
      ]
    },
    {
      "name": "魏延",
      "skills": [
        "子午奇谋",
        "锐不可当",
        "胜敌益强"
      ]
    },
    {
      "name": "诸葛亮2",
      "skills": [
        "星罗棋布",
        "疾行侧击",
        "折冲御侮"
      ]
    }
  ],
  "winner": "2",
  "fuzzy_match_failures": []
}