{
  "1": [
    {
      "name": "乐进",
      "skills": [
        "每战先登",
        "无难之志",
        "料事如神"
      ]
    },
    {
      "name": "曹纯",
      "skills": [
        "天下骁锐",
        "铸甲销戈",
        "舍生取义"
      ]
    },
    {
      "name": "马云禄",
      "skills": [
        "红妆缭乱",
        "弓腰姬",
        "摧坚克难"
      ]
    }
  ],
  "2": [
    {
      "name": "鲁肃",
      "skills": [
        "划湘分荆",
        "知人善任",
        "风助火势"
      ]
    },
    {
      "name": "孙权",
      "skills": [
        "虎踞江东",
        "烈火张天",
        "料事如神"
      ]
    },
    {
      "name": "陆逊",
      "skills": [
        "火烧连营",
        "明其虚实",
        "韬光养晦"
      ]
    }
  ],
  "winner": "2",
  "fuzzy_match_failures": []
}