{
  "1": [
    {
      "name": "祝融",
      "skills": [
        "南疆烈刃",
        "锐不可当",
        "胜敌益强"
      ]
    },
    {
      "name": "孟获",
      "skills": [
        "雄护南疆",
        "披坚执锐",
        "同舟共济"
      ]
    },
    {
      "name": "董卓",
      "skills": [
        "权倾朝野",
        "步步为营",
        "战八方"
      ]
    }
  ],
  "2": [
    {
      "name": "张宁",
      "skills": [
        "太平余响",
        "建计举人",
        "明其虚实"
      ]
    },
    {
      "name": "田丰",
      "skills": [
        "荐计阻敌",
        "如有神助",
        "黄天惑心"
      ]
    },
    {
      "name": "荀彧",
      "skills": [
        "建计举人",
        "避其锐气",
        "料事如神"
      ]
    }
  ],
  "winner": "1",
  "fuzzy_match_failures": []
}