{
  "1": [
    {
      "name": "木鹿大王",
      "skills": [
        "驱兽御象",
        "烈火张天",
        "风助火势"
      ]
    },
    {
      "name": "鲁肃",
      "skills": [
        "划湘分荆",
        "知人善任",
        "任人唯贤"
      ]
    },
    {
      "name": "张宁",
      "skills": [
        "太平余响",
        "明其虚实",
        "出其不意"
      ]
    }
  ],
  "2": [
    {
      "name": "袁术",
      "skills": [
        "僭号天子",
        "如沐春风",
        "蓄势待发"
      ]
    },
    {
      "name": "皇甫嵩2",
      "skills": [
        "兵动若神",
        "洗筋伐髓",
        "忘私相助"
      ]
    },
    {
      "name": "朱儁",
      "skills": [
        "围师必阙",
        "未雨绸缪",
        "烈火焚营"
      ]
    }
  ],
  "winner": "2",
  "fuzzy_match_failures": []
}