{
  "1": [
    {
      "name": "袁绍",
      "skills": [
        "合聚群雄",
        "文武双全",
        "惩前毖后"
      ]
    },
    {
      "name": "小乔",
      "skills": [
        "天香",
        "奇门遁甲",
        "烈火焚营"
      ]
    },
    {
      "name": "关羽",
      "skills": [
        "威震华夏",
        "破阵驰围",
        "破军袭敌"
      ]
    }
  ],
  "2": [
    {
      "name": "左慈",
      "skills": [
        "云行雨施",
        "折冲御侮",
        "践墨随敌"
      ]
    },
    {
      "name": "孙坚2",
      "skills": [
        "诛凶殄逆",
        "任人唯贤",
        "十面埋伏"
      ]
    },
    {
      "name": "张宁",
      "skills": [
        "太平余响",
        "黄天惑心",
        "洗筋伐髓"
      ]
    }
  ],
  "winner": "2",
  "fuzzy_match_failures": []
}