{
  "1": [
    {
      "name": "诸葛瑾",
      "skills": [
        "慎思笃行",
        "固若金汤",
        "践墨随敌"
      ]
    },
    {
      "name": "荀彧",
      "skills": [
        "建计举人",
        "烈火张天",
        "料事如神"
      ]
    },
    {
      "name": "周瑜",
      "skills": [
        "临机制胜",
        "王佐之才",
        "断敌粮道"
      ]
    }
  ],
  "2": [
    {
      "name": "田丰",
      "skills": [
        "荐计阻敌",
        "料事如神",
        "避其锐气"
      ]
    },
    {
      "name": "庞统",
      "skills": [
        "连环计",
        "铸甲销戈",
        "决水破敌"
      ]
    },
    {
      "name": "马云禄",
      "skills": [
        "红妆缭乱",
        "定军扬威",
        "水淹七军"
      ]
    }
  ],
  "winner": "1",
  "fuzzy_match_failures": []
}