{
  "1": [
    {
      "name": "左慈",
      "skills": [
        "云行雨施",
        "折冲御侮",
        "鸩饮毒弑"
      ]
    },
    {
      "name": "陆抗",
      "skills": [
        "决堰倾涛",
        "黄天惑心",
        "风助火势"
      ]
    },
    {
      "name": "张宁",
      "skills": [
        "太平余响",
        "烈火焚营",
        "胜敌益强"
      ]
    }
  ],
  "2": [
    {
      "name": "大乔",
      "skills": [
        "国色",
        "坚如磐石",
        "鸩饮毒弑"
      ]
    },
    {
      "name": "黄盖",
      "skills": [
        "苦肉计",
        "战八方",
        "黄天惑心"
      ]
    },
    {
      "name": "诸葛亮",
      "skills": [
        "草船借箭",
        "运智铺谋",
        "谋而后动"
      ]
    }
  ],
  "winner": "1",
  "fuzzy_match_failures": []
}