{
  "1": [
    {
      "name": "陆逊",
      "skills": [
        "火烧连营",
        "烈火焚营",
        "洗筋伐髓"
      ]
    },
    {
      "name": "陆抗",
      "skills": [
        "决堰倾涛",
        "流风回雪",
        "神略制变"
      ]
    },
    {
      "name": "鲁肃",
      "skills": [
        "划湘分荆",
        "狂风大作",
        "烈火张天"
      ]
    }
  ],
  "2": [
    {
      "name": "夏侯惇",
      "skills": [
        "刚烈",
        "横征暴敛",
        "蹈锋饮血"
      ]
    },
    {
      "name": "诸葛亮",
      "skills": [
        "草船借箭",
        "惩前毖后",
        "指点乾坤"
      ]
    },
    {
      "name": "司马懿",
      "skills": [
        "鹰视狼顾",
        "未雨绸缪",
        "断敌粮道"
      ]
    }
  ],
  "winner": "2",
  "fuzzy_match_failures": []
}