{
  "1": [
    {
      "name": "黄盖",
      "skills": [
        "苦肉计",
        "战八方",
        "风助火势"
      ]
    },
    {
      "name": "法正",
      "skills": [
        "睹事知机",
        "建计举人",
        "黄天惑心"
      ]
    },
    {
      "name": "周瑜",
      "skills": [
        "临机制胜",
        "胜敌益强",
        "机变无穷"
      ]
    }
  ],
  "2": [
    {
      "name": "黄盖",
      "skills": [
        "苦肉计",
        "烈火张天",
        "横征暴敛"
      ]
    },
    {
      "name": "张昭",
      "skills": [
        "直谏固政",
        "铸甲销戈",
        "建计举人"
      ]
    },
    {
      "name": "陆逊",
      "skills": [
        "火烧连营",
        "明其虚实",
        "韬光养晦"
      ]
    }
  ],
  "winner": "1",
  "fuzzy_match_failures": []
}