{
  "1": [
    {
      "name": "周瑜",
      "skills": [
        "临机制胜",
        "王佐之才",
        "潜龙在渊"
      ]
    },
    {
      "name": "黄盖",
      "skills": [
        "苦肉计",
        "烈火张天",
        "金城汤池"
      ]
    },
    {
      "name": "周泰",
      "skills": [
        "不屈意志",
        "挫锐折锋",
        "避其锐气"
      ]
    }
  ],
  "2": [
    {
      "name": "左慈",
      "skills": [
        "云行雨施",
        "避其锐气",
        "神略制变"
      ]
    },
    {
      "name": "朱儁",
      "skills": [
        "围师必阙",
        "文武双全",
        "黄天惑心"
      ]
    },
    {
      "name": "张宁",
      "skills": [
        "太平余响",
        "王佐之才",
        "烈火焚营"
      ]
    }
  ],
  "winner": "2",
  "fuzzy_match_failures": []
}